foobarstats/__init__.py
foobarstats/models.py
foobarstats/parser.py
foobarstats-0.1.0.dist-info/METADATA
foobarstats-0.1.0.dist-info/WHEEL
foobarstats-0.1.0.dist-info/licenses/LICENSE
foobarstats-0.1.0.dist-info/RECORD
