Metadata-Version: 2.4
Name: foobarstats
Version: 0.1.0
Summary: A lightweight library for parsing foobar2000 XML statistics into Pydantic models
License: MIT
License-File: LICENSE
Keywords: foobar2000,audio,parser
Author: Olezhich
Requires-Python: >=3.10
Classifier: License :: OSI Approved :: MIT License
Classifier: Programming Language :: Python :: 3
Classifier: Programming Language :: Python :: 3.10
Classifier: Programming Language :: Python :: 3.11
Classifier: Programming Language :: Python :: 3.12
Classifier: Programming Language :: Python :: 3.13
Classifier: Programming Language :: Python :: 3.14
Requires-Dist: pydantic (>=2.12.2,<3.0.0)
